[
    { "title": "A kind of magic", "id": 0, "duration": "5:20", "intro": "VOICE+4 (133)" },
    { "title": "Another brick in the wall", "id": 1, "duration": "6:40", "intro": "DAVE" },
    { "title": "Axel F - The heat is on", "id": 2, "duration": "5:02", "intro": "CASSA+Dave (118/151)" },
    { "title": "Baby I love you - Freeway", "id": 3, "duration": "3:45", "intro": "KEYB+4 (130/145)" },
    { "title": "Blues Brothers Mix", "id": 4, "duration": "7:00", "intro": "1,2-1,2,3,4  (190)" },
    { "title": "Buffy main theme", "id": 5, "duration": "1:05", "intro": "KEYB+1,2,3,4" },
    { "title": "Far from over", "id": 6, "duration": "3:15", "intro": "1,2,3,4 (173)" },
    { "title": "Footloose", "id": 7, "duration": "2:53", "intro": "DRUMS (174)" },
    { "title": "Ghostbusters", "id": 8, "duration": "3:57", "intro": "BASE" },
    { "title": "Greased Lightnin'", "id": 9, "duration": "3:00", "intro": "Robb (160)" },
    { "title": "Happy Days", "id": 10, "duration": "1:15", "intro": "1,2-1,2,3,4 (193)" },
    { "title": "Hearts on fire", "id": 11, "duration": "4:15", "intro": "1,2,3,4" },
    { "title": "I'll be there for you", "id": 12, "duration": "3:05", "intro": "GUIT (196)" },
    { "title": "Il padrino", "id": 13, "duration": "2:50", "intro": "" },
    { "title": "Johnny B. Goode - The power of love", "id": 14, "duration": "4:40", "intro": "GUIT (170/118)" },
    { "title": "Jump", "id": 15, "duration": "4:00", "intro": "DAVE" },
    { "title": "Maniac", "id": 16, "duration": "4:15", "intro": "Base+Drums (159)" },
    { "title": "Master Of Puppets", "id": 17, "duration": "3:15", "intro": "1,2-1,2,3,4" },
    { "title": "Mix Super Car Magnum PI", "id": 18, "duration": "2:00", "intro": "Fabry Nirvana (135)" },
    { "title": "Nano Nano", "id": 19, "duration": "2:40", "intro": "1,2,3,4 (158)" },
    { "title": "No easy way out", "id": 20, "duration": "4:18", "intro": "BASE" },
    { "title": "Pretty woman", "id": 21, "duration": "2:30", "intro": "1,2,3,4 (134)" },
    { "title": "Reality", "id": 22, "duration": "4:45", "intro": "FABRY" },
    { "title": "The Final Countdown", "id": 23, "duration": "5:40", "intro": "BASE" },
    { "title": "The Neverending Story", "id": 24, "duration": "3:35", "intro": "BASE" },
    { "title": "The eye of the tiger", "id": 25, "duration": "3:50", "intro": "GUIT (110)" },
    { "title": "The time of my life", "id": 26, "duration": "4:50", "intro": "1,2,3,4" },
    { "title": "Top Gun Anthem - Mighty Wings - Danger zone", "id": 27, "duration": "7:41", "intro": "BASE (108/159/159)" },
    { "title": "You can leave your hat on", "id": 28, "duration": "4:45", "intro": "1,2,3 (88)" },
    { "title": "You're the best", "id": 29, "duration": "2:43", "intro": "CASSA+ 1,2,3,4 (100)" }
]